invoice/__init__.py
invoice/admin.py
invoice/apps.py
invoice/mixins.py
invoice/models.py
invoice/schema.py
invoice/signals.py
invoice/urls.py
invoice/utils.py
invoice/views.py
invoice/gql/__init__.py
invoice/gql/filter_mixin.py
invoice/gql/input_types.py
invoice/gql/query_mixins.py
invoice/gql/bill/__init__.py
invoice/gql/bill/mutation.py
invoice/gql/bill/query.py
invoice/gql/bill_event/__init__.py
invoice/gql/bill_event/mutation.py
invoice/gql/bill_event/query.py
invoice/gql/bill_item/__init__.py
invoice/gql/bill_item/mutation.py
invoice/gql/bill_item/query.py
invoice/gql/bill_payment/__init__.py
invoice/gql/bill_payment/mutation.py
invoice/gql/bill_payment/query.py
invoice/gql/detail_payment_invoice/__init__.py
invoice/gql/detail_payment_invoice/mutation.py
invoice/gql/detail_payment_invoice/query.py
invoice/gql/gql_types/__init__.py
invoice/gql/gql_types/bill_types.py
invoice/gql/gql_types/invoice_types.py
invoice/gql/gql_types/payment_types.py
invoice/gql/invoice/__init__.py
invoice/gql/invoice/mutation.py
invoice/gql/invoice/query.py
invoice/gql/invoice_event/__init__.py
invoice/gql/invoice_event/mutation.py
invoice/gql/invoice_event/query.py
invoice/gql/invoice_line_item/__init__.py
invoice/gql/invoice_line_item/mutation.py
invoice/gql/invoice_line_item/query.py
invoice/gql/invoice_payment/__init__.py
invoice/gql/invoice_payment/mutation.py
invoice/gql/invoice_payment/query.py
invoice/gql/payment_invoice/__init__.py
invoice/gql/payment_invoice/mutation.py
invoice/gql/payment_invoice/query.py
invoice/migrations/0001_initial_migration.py
invoice/migrations/0002_auto_20211117_0904.py
invoice/migrations/0003_auto_20211203_1053.py
invoice/migrations/0004_invoice_bill_roles_for_admin.py
invoice/migrations/0005_invoice_bill_roles_for_accountant.py
invoice/migrations/0006_detailpaymentinvoice_historicaldetailpaymentinvoice_historicalpaymentinvoice_paymentinvoice.py
invoice/migrations/0007_auto_20220411_1053.py
invoice/migrations/0008_auto_20220411_1358.py
openimis_be_invoice-1.10.0.dist-info/licenses/LICENSE
openimis_be_invoice-1.10.0.dist-info/METADATA
openimis_be_invoice-1.10.0.dist-info/WHEEL
openimis_be_invoice-1.10.0.dist-info/top_level.txt
openimis_be_invoice-1.10.0.dist-info/RECORD
